<?xml version="1.0" encoding="UTF-8"?><Document>
    <de.tudarmstadt.ukp.dkpro.core.api.metadata.type.DocumentMetaData sofa="Sofa" begin="0" end="163" language="x-unspecified" documentTitle="фольклорный%20архив~3.2.%20загадки%20(один%20льёт...).txt" documentId="INITIAL_CAS" documentUri="file:/export/repository/project/6794/document/28463/source/INITI..." collectionId="file:/export/repository/project/6794/document/28463/source/" documentBaseUri="file:/export/repository/project/6794/document/28463/source/" isLastSegment="false">
        <de.tudarmstadt.ukp.dkpro.core.api.segmentation.type.Sentence sofa="Sofa" begin="0" end="50" id="null">
            <de.tudarmstadt.ukp.dkpro.core.api.segmentation.type.Token sofa="Sofa" begin="0" end="4" parent="null" lemma="null" stem="null" pos="null" morph="null" id="null" form="null" syntacticFunction="null" order="0">
                <de.tudarmstadt.ukp.dkpro.core.api.metadata.type.TagsetDescription sofa="Sofa" begin="0" end="0" layer="de.tudarmstadt.ukp.dkpro.core.api.syntax.type.dependency.Depende..." name="UD Universal Dependencies (v2)" tags="null" componentName="null" modelLocation="null" modelVariant="null" modelLanguage="null" modelVersion="null" input="false"/>
                <de.tudarmstadt.ukp.dkpro.core.api.metadata.type.TagsetDescription sofa="Sofa" begin="0" end="0" layer="de.tudarmstadt.ukp.dkpro.core.api.ner.type.NamedEntity" name="Named Entity tags" tags="null" componentName="null" modelLocation="null" modelVariant="null" modelLanguage="null" modelVersion="null" input="false"/>
                <de.tudarmstadt.ukp.dkpro.core.api.metadata.type.TagsetDescription sofa="Sofa" begin="0" end="0" layer="de.tudarmstadt.ukp.dkpro.core.api.transform.type.SofaChangeAnnot..." name="Operation" tags="null" componentName="null" modelLocation="null" modelVariant="null" modelLanguage="null" modelVersion="null" input="false"/>
                <de.tudarmstadt.ukp.dkpro.core.api.metadata.type.TagsetDescription sofa="Sofa" begin="0" end="0" layer="de.tudarmstadt.ukp.dkpro.core.api.lexmorph.type.pos.POS" name="UD Universal POS tags (v2)" tags="null" componentName="null" modelLocation="null" modelVariant="null" modelLanguage="null" modelVersion="null" input="false"/>
                <de.tudarmstadt.ukp.dkpro.core.api.metadata.type.TagsetDescription sofa="Sofa" begin="0" end="0" layer="custom.Span" name="Span labels" tags="null" componentName="null" modelLocation="null" modelVariant="null" modelLanguage="null" modelVersion="null" input="false"/>
                Один
            </de.tudarmstadt.ukp.dkpro.core.api.segmentation.type.Token>
             
            <de.tudarmstadt.ukp.dkpro.core.api.segmentation.type.Token sofa="Sofa" begin="5" end="9" parent="null" lemma="null" stem="null" pos="null" morph="null" id="null" form="null" syntacticFunction="null" order="0">льёт</de.tudarmstadt.ukp.dkpro.core.api.segmentation.type.Token>
            <de.tudarmstadt.ukp.dkpro.core.api.segmentation.type.Token sofa="Sofa" begin="9" end="10" parent="null" lemma="null" stem="null" pos="null" morph="null" id="null" form="null" syntacticFunction="null" order="0">,</de.tudarmstadt.ukp.dkpro.core.api.segmentation.type.Token>
             
            <de.tudarmstadt.ukp.dkpro.core.api.segmentation.type.Token sofa="Sofa" begin="11" end="17" parent="null" lemma="null" stem="null" pos="null" morph="null" id="null" form="null" syntacticFunction="null" order="0">другой</de.tudarmstadt.ukp.dkpro.core.api.segmentation.type.Token>
             
            <de.tudarmstadt.ukp.dkpro.core.api.segmentation.type.Token sofa="Sofa" begin="18" end="22" parent="null" lemma="null" stem="null" pos="null" morph="null" id="null" form="null" syntacticFunction="null" order="0">пьёт</de.tudarmstadt.ukp.dkpro.core.api.segmentation.type.Token>
            <de.tudarmstadt.ukp.dkpro.core.api.segmentation.type.Token sofa="Sofa" begin="22" end="23" parent="null" lemma="null" stem="null" pos="null" morph="null" id="null" form="null" syntacticFunction="null" order="0">,</de.tudarmstadt.ukp.dkpro.core.api.segmentation.type.Token>
             
            <de.tudarmstadt.ukp.dkpro.core.api.segmentation.type.Token sofa="Sofa" begin="24" end="30" parent="null" lemma="null" stem="null" pos="null" morph="null" id="null" form="null" syntacticFunction="null" order="0">третий</de.tudarmstadt.ukp.dkpro.core.api.segmentation.type.Token>
             
            <de.tudarmstadt.ukp.dkpro.core.api.segmentation.type.Token sofa="Sofa" begin="31" end="39" parent="null" lemma="null" stem="null" pos="null" morph="null" id="null" form="null" syntacticFunction="null" order="0">зеленеет</de.tudarmstadt.ukp.dkpro.core.api.segmentation.type.Token>
             
            <de.tudarmstadt.ukp.dkpro.core.api.segmentation.type.Token sofa="Sofa" begin="40" end="42" parent="null" lemma="null" stem="null" pos="null" morph="null" id="null" form="null" syntacticFunction="null" order="0">да</de.tudarmstadt.ukp.dkpro.core.api.segmentation.type.Token>
             
            <de.tudarmstadt.ukp.dkpro.core.api.segmentation.type.Token sofa="Sofa" begin="43" end="49" parent="null" lemma="null" stem="null" pos="null" morph="null" id="null" form="null" syntacticFunction="null" order="0">растёт</de.tudarmstadt.ukp.dkpro.core.api.segmentation.type.Token>
            <de.tudarmstadt.ukp.dkpro.core.api.segmentation.type.Token sofa="Sofa" begin="49" end="50" parent="null" lemma="null" stem="null" pos="null" morph="null" id="null" form="null" syntacticFunction="null" order="0">.</de.tudarmstadt.ukp.dkpro.core.api.segmentation.type.Token>
        </de.tudarmstadt.ukp.dkpro.core.api.segmentation.type.Sentence>
         
        <de.tudarmstadt.ukp.dkpro.core.api.segmentation.type.Sentence sofa="Sofa" begin="51" end="122" id="null">
            <de.tudarmstadt.ukp.dkpro.core.api.segmentation.type.Token sofa="Sofa" begin="51" end="52" parent="null" lemma="null" stem="null" pos="null" morph="null" id="null" form="null" syntacticFunction="null" order="0">(</de.tudarmstadt.ukp.dkpro.core.api.segmentation.type.Token>
            <de.tudarmstadt.ukp.dkpro.core.api.segmentation.type.Token sofa="Sofa" begin="52" end="57" parent="null" lemma="null" stem="null" pos="null" morph="null" id="null" form="null" syntacticFunction="null" order="0">дождь</de.tudarmstadt.ukp.dkpro.core.api.segmentation.type.Token>
            <de.tudarmstadt.ukp.dkpro.core.api.segmentation.type.Token sofa="Sofa" begin="57" end="58" parent="null" lemma="null" stem="null" pos="null" morph="null" id="null" form="null" syntacticFunction="null" order="0">,</de.tudarmstadt.ukp.dkpro.core.api.segmentation.type.Token>
             
            <de.tudarmstadt.ukp.dkpro.core.api.segmentation.type.Token sofa="Sofa" begin="59" end="64" parent="null" lemma="null" stem="null" pos="null" morph="null" id="null" form="null" syntacticFunction="null" order="0">земля</de.tudarmstadt.ukp.dkpro.core.api.segmentation.type.Token>
             
            <de.tudarmstadt.ukp.dkpro.core.api.segmentation.type.Token sofa="Sofa" begin="65" end="66" parent="null" lemma="null" stem="null" pos="null" morph="null" id="null" form="null" syntacticFunction="null" order="0">и</de.tudarmstadt.ukp.dkpro.core.api.segmentation.type.Token>
             
            <de.tudarmstadt.ukp.dkpro.core.api.segmentation.type.Token sofa="Sofa" begin="67" end="71" parent="null" lemma="null" stem="null" pos="null" morph="null" id="null" form="null" syntacticFunction="null" order="0">хлеб</de.tudarmstadt.ukp.dkpro.core.api.segmentation.type.Token>
            <de.tudarmstadt.ukp.dkpro.core.api.segmentation.type.Token sofa="Sofa" begin="71" end="72" parent="null" lemma="null" stem="null" pos="null" morph="null" id="null" form="null" syntacticFunction="null" order="0">)</de.tudarmstadt.ukp.dkpro.core.api.segmentation.type.Token>
            &#13;
&#13;

            <de.tudarmstadt.ukp.dkpro.core.api.segmentation.type.Token sofa="Sofa" begin="76" end="86" parent="null" lemma="null" stem="null" pos="null" morph="null" id="null" form="null" syntacticFunction="null" order="0">Собиратель</de.tudarmstadt.ukp.dkpro.core.api.segmentation.type.Token>
             
            <de.tudarmstadt.ukp.dkpro.core.api.segmentation.type.Token sofa="Sofa" begin="87" end="96" parent="null" lemma="null" stem="null" pos="null" morph="null" id="null" form="null" syntacticFunction="null" order="0">Гринштейн</de.tudarmstadt.ukp.dkpro.core.api.segmentation.type.Token>
            <de.tudarmstadt.ukp.dkpro.core.api.segmentation.type.Token sofa="Sofa" begin="96" end="97" parent="null" lemma="null" stem="null" pos="null" morph="null" id="null" form="null" syntacticFunction="null" order="0">,</de.tudarmstadt.ukp.dkpro.core.api.segmentation.type.Token>
             
            <de.tudarmstadt.ukp.dkpro.core.api.segmentation.type.Token sofa="Sofa" begin="98" end="102" parent="null" lemma="null" stem="null" pos="null" morph="null" id="null" form="null" syntacticFunction="null" order="0">1989</de.tudarmstadt.ukp.dkpro.core.api.segmentation.type.Token>
             
            <de.tudarmstadt.ukp.dkpro.core.api.segmentation.type.Token sofa="Sofa" begin="103" end="106" parent="null" lemma="null" stem="null" pos="null" morph="null" id="null" form="null" syntacticFunction="null" order="0">год</de.tudarmstadt.ukp.dkpro.core.api.segmentation.type.Token>
            <de.tudarmstadt.ukp.dkpro.core.api.segmentation.type.Token sofa="Sofa" begin="106" end="107" parent="null" lemma="null" stem="null" pos="null" morph="null" id="null" form="null" syntacticFunction="null" order="0">,</de.tudarmstadt.ukp.dkpro.core.api.segmentation.type.Token>
             
            <de.tudarmstadt.ukp.dkpro.core.api.segmentation.type.Token sofa="Sofa" begin="108" end="113" parent="null" lemma="null" stem="null" pos="null" morph="null" id="null" form="null" syntacticFunction="null" order="0">город</de.tudarmstadt.ukp.dkpro.core.api.segmentation.type.Token>
             
            <de.tudarmstadt.ukp.dkpro.core.api.segmentation.type.Token sofa="Sofa" begin="114" end="121" parent="null" lemma="null" stem="null" pos="null" morph="null" id="null" form="null" syntacticFunction="null" order="0">Иркутск</de.tudarmstadt.ukp.dkpro.core.api.segmentation.type.Token>
            <de.tudarmstadt.ukp.dkpro.core.api.segmentation.type.Token sofa="Sofa" begin="121" end="122" parent="null" lemma="null" stem="null" pos="null" morph="null" id="null" form="null" syntacticFunction="null" order="0">.</de.tudarmstadt.ukp.dkpro.core.api.segmentation.type.Token>
        </de.tudarmstadt.ukp.dkpro.core.api.segmentation.type.Sentence>
        &#13;

        <de.tudarmstadt.ukp.dkpro.core.api.segmentation.type.Sentence sofa="Sofa" begin="124" end="163" id="null">
            <de.tudarmstadt.ukp.dkpro.core.api.segmentation.type.Token sofa="Sofa" begin="124" end="129" parent="null" lemma="null" stem="null" pos="null" morph="null" id="null" form="null" syntacticFunction="null" order="0">Набор</de.tudarmstadt.ukp.dkpro.core.api.segmentation.type.Token>
             
            <de.tudarmstadt.ukp.dkpro.core.api.segmentation.type.Token sofa="Sofa" begin="130" end="136" parent="null" lemma="null" stem="null" pos="null" morph="null" id="null" form="null" syntacticFunction="null" order="0">текста</de.tudarmstadt.ukp.dkpro.core.api.segmentation.type.Token>
            <de.tudarmstadt.ukp.dkpro.core.api.segmentation.type.Token sofa="Sofa" begin="136" end="137" parent="null" lemma="null" stem="null" pos="null" morph="null" id="null" form="null" syntacticFunction="null" order="0">:</de.tudarmstadt.ukp.dkpro.core.api.segmentation.type.Token>
             
            <de.tudarmstadt.ukp.dkpro.core.api.segmentation.type.Token sofa="Sofa" begin="138" end="146" parent="null" lemma="null" stem="null" pos="null" morph="null" id="null" form="null" syntacticFunction="null" order="0">Лебедева</de.tudarmstadt.ukp.dkpro.core.api.segmentation.type.Token>
             
            <de.tudarmstadt.ukp.dkpro.core.api.segmentation.type.Token sofa="Sofa" begin="147" end="150" parent="null" lemma="null" stem="null" pos="null" morph="null" id="null" form="null" syntacticFunction="null" order="0">З.М</de.tudarmstadt.ukp.dkpro.core.api.segmentation.type.Token>
            <de.tudarmstadt.ukp.dkpro.core.api.segmentation.type.Token sofa="Sofa" begin="150" end="151" parent="null" lemma="null" stem="null" pos="null" morph="null" id="null" form="null" syntacticFunction="null" order="0">.</de.tudarmstadt.ukp.dkpro.core.api.segmentation.type.Token>
            <de.tudarmstadt.ukp.dkpro.core.api.segmentation.type.Token sofa="Sofa" begin="151" end="152" parent="null" lemma="null" stem="null" pos="null" morph="null" id="null" form="null" syntacticFunction="null" order="0">,</de.tudarmstadt.ukp.dkpro.core.api.segmentation.type.Token>
             
            <de.tudarmstadt.ukp.dkpro.core.api.segmentation.type.Token sofa="Sofa" begin="153" end="163" parent="null" lemma="null" stem="null" pos="null" morph="null" id="null" form="null" syntacticFunction="null" order="0">25.06.2022</de.tudarmstadt.ukp.dkpro.core.api.segmentation.type.Token>
        </de.tudarmstadt.ukp.dkpro.core.api.segmentation.type.Sentence>
    </de.tudarmstadt.ukp.dkpro.core.api.metadata.type.DocumentMetaData>
</Document>
